alias_gen/__init__.py
alias_gen/aliaser.py
alias_gen/arg_parser.py
alias_gen/constants.py
alias_gen/file_utils.py
alias_gen/logger.py
alias_gen-0.6.7.dist-info/LICENSE.md
alias_gen-0.6.7.dist-info/METADATA
alias_gen-0.6.7.dist-info/WHEEL
alias_gen-0.6.7.dist-info/entry_points.txt
alias_gen-0.6.7.dist-info/RECORD
