Metadata-Version: 2.1
Name: alias-gen
Version: 0.6.7
Summary: Generate bash/zsh/fish shell aliases automatically.
License: MIT
Keywords: alias,bash,zsh,fish,shell,cli,command-line,command,completion,abbr,generate,terminal
Author: Ariel Frischer
Author-email: arielfrischer@gmail.com
Maintainer: Ariel Frischer
Maintainer-email: arielfrischer@gmail.com
Classifier: License :: OSI Approved :: MIT License
Classifier: Operating System :: OS Independent
Classifier: Programming Language :: Python :: 2
Classifier: Programming Language :: Python :: 2.7
Classifier: Programming Language :: Python :: 3
Classifier: Programming Language :: Python :: 3.4
Classifier: Programming Language :: Python :: 3.5
Classifier: Programming Language :: Python :: 3.6
Classifier: Programming Language :: Python :: 3.7
Classifier: Programming Language :: Python :: 3.8
Classifier: Programming Language :: Python :: 3.9
Classifier: Programming Language :: Python :: 3.10
Classifier: Programming Language :: Python :: 3.11
